adr_writer/__init__.py
adr_writer/__main__.py
adr_writer-1.1.3.dist-info/METADATA
adr_writer-1.1.3.dist-info/WHEEL
adr_writer-1.1.3.dist-info/RECORD
