Metadata-Version: 2.1
Name: adr_writer
Version: 1.1.3
Summary: Create Architecture Decision Records by answering questions to ensure consistency in formatting and thought processes.
Home-page: https://gitlab.com/fer1035_python/modules/pypi-adr_writer
License: GPL-2.0-only
Keywords: adr,writer,architecture,decision,record
Author: Ahmad Ferdaus Abd Razak
Author-email: ahmad.ferdaus.abd.razak@ni.com
Requires-Python: >=3.9,<4.0
Classifier: License :: OSI Approved :: GNU General Public License v2 (GPLv2)
Classifier: Programming Language :: Python :: 3
Classifier: Programming Language :: Python :: 3.9
Classifier: Programming Language :: Python :: 3.10
Classifier: Programming Language :: Python :: 3.11
Classifier: Programming Language :: Python :: 3.12
Project-URL: Repository, https://gitlab.com/fer1035_python/modules/pypi-adr_writer
